poi_sdk/__init__.py
poi_sdk/cli.py
poi_sdk/config.py
poi_sdk/exceptions.py
poi_sdk/generator.py
poi_sdk/py.typed
poi_sdk/receipt.py
poi_sdk/validator.py
poi_sdk-0.1.0.dist-info/licenses/LICENSE
poi_sdk-0.1.0.dist-info/METADATA
poi_sdk-0.1.0.dist-info/WHEEL
poi_sdk-0.1.0.dist-info/entry_points.txt
poi_sdk-0.1.0.dist-info/top_level.txt
poi_sdk-0.1.0.dist-info/RECORD
